{"name": "Bellerophon", "url": "https://en.wikipedia.org/wiki/Bellerophon", "type": "heroes", "pantheon": "Greek", "description": "Bellerophon&#91;1&#93; or Bellerophontes (Ancient Greek: Βελλεροφῶν; Βελλεροφόντης, lit.&#8201;'slayer of Belleros') or Hipponous (Ancient Greek: Ἱππόνοος, lit.&#8201;'horse-knower'),&#91;2&#93; was a divine Corinthian hero of Greek mythology, the son of Poseidon and Eurynome, and the foster son of Glaukos. He was \"the greatest hero and slayer of monsters, alongside Cadmus and Perseus, before the days of Heracles\".&#91;3&#93; Among his greatest feats was killing the Chimera of the Iliad, a monster that Homer depicted with a lion's head, a goat's body, and a serpent's tail: \"her breath came out", "infobox": {"Other names": "Hipponous", "Predecessor": "Iobates", "Successor": "Hippolochus", "Abode": "Potniae, later Argos and Lycia", "Symbols": "Cape, Spear", "Parents": "Poseidon and EurynomeGlaucus and Eurymede", "Siblings": "Deliades and several paternal half-siblings", "Consort": "PhilonoeAsteria", "Offspring": "Isander, Hippolochus and LaodamiaHydissos"}, "aliases": [], "archetypes": [], "archetype_scores": {}}