{"name": "Búri", "url": "https://en.wikipedia.org/wiki/B%C3%BAri", "type": "deities", "pantheon": "Norse", "description": "In Norse mythology, Búri (Old Norse: &#91;ˈbuːre&#93;) is a divinity god 'producer, father' of all other gods,&#91;1&#93; and an early ancestor of the Æsir gods of the principal pantheon in Old Norse religion. Búri was licked free from salty rime stones by the primeval cow Auðumbla over the course of three days. Búri's background beyond this point is unattested, and he had a son, Borr, by way of an unknown process. Búri is attested in the Prose Edda, composed in the 13th century by Icelander Snorri Sturluson. The Prose Edda includes a quote from a 12th-century poem by skald Þórvaldr Blönduskál", "infobox": {}, "aliases": [], "archetypes": [], "archetype_scores": {}}